toot_mcp/__init__.py
toot_mcp/toot_mcp.py
toot_mcp-0.1.1.dist-info/licenses/LICENSE
toot_mcp-0.1.1.dist-info/METADATA
toot_mcp-0.1.1.dist-info/WHEEL
toot_mcp-0.1.1.dist-info/top_level.txt
toot_mcp-0.1.1.dist-info/RECORD
