Metadata-Version: 2.4
Name: toot-mcp
Version: 0.1.1
Summary: Train of Thought (TOOT) MCP for validated conceptual reasoning chains
Author-email: Isaac <isaac@example.com>
License: GNOSYS Personal Builder License (GPBL) v1.0
License-File: LICENSE
Requires-Dist: fastmcp>=2.0.0
Requires-Dist: pydantic>=2.0.0
Provides-Extra: dev
Requires-Dist: pytest; extra == "dev"
Requires-Dist: black; extra == "dev"
Requires-Dist: isort; extra == "dev"
Dynamic: license-file
